{
  "name": "Upsert contact in Salesforce",
  "version": 2,
  "private": true,
  "concurrency": 1,
  "code": {
    "number": 0,
    "provider": "workato_api_platform",
    "name": "receive_request",
    "as": "058c38c2",
    "keyword": "trigger",
    "dynamicPickListSelection": {
      "response.responses.0.http_status_code": "201 - Created",
      "response.responses.1.http_status_code": "400 - Bad Request"
    },
    "toggleCfg": {
      "response.responses.0.http_status_code": true,
      "response.responses.1.http_status_code": true
    },
    "input": {
      "request": {
        "content_type": "json",
        "schema": "[{\"control_type\":\"text\",\"label\":\"ID\",\"type\":\"string\",\"name\":\"id\",\"optional\":true},{\"control_type\":\"text\",\"label\":\"Last name\",\"type\":\"string\",\"name\":\"LastName\"},{\"control_type\":\"text\",\"label\":\"Account ID\",\"type\":\"string\",\"name\":\"AccountId\",\"optional\":true},{\"control_type\":\"text\",\"label\":\"Email\",\"type\":\"string\",\"name\":\"Email\",\"optional\":true},{\"control_type\":\"text\",\"label\":\"First name\",\"type\":\"string\",\"name\":\"FirstName\",\"optional\":true},{\"control_type\":\"text\",\"label\":\"Home phone\",\"type\":\"string\",\"name\":\"HomePhone\",\"optional\":true},{\"control_type\":\"text\",\"label\":\"Mailing city\",\"type\":\"string\",\"name\":\"MailingCity\",\"optional\":true},{\"control_type\":\"text\",\"label\":\"Mailing country\",\"type\":\"string\",\"name\":\"MailingCountry\",\"optional\":true},{\"control_type\":\"text\",\"label\":\"Mailing state\",\"type\":\"string\",\"name\":\"MailingState\",\"optional\":true},{\"control_type\":\"text\",\"label\":\"Mailing street\",\"type\":\"string\",\"name\":\"MailingStreet\",\"optional\":true},{\"control_type\":\"text\",\"label\":\"Mailing postal code\",\"type\":\"string\",\"name\":\"MailingPostalCode\",\"optional\":true},{\"control_type\":\"text\",\"label\":\"Assistant name\",\"type\":\"string\",\"name\":\"AssistantName\",\"optional\":true},{\"control_type\":\"text\",\"label\":\"Assistant phone\",\"type\":\"string\",\"name\":\"AssistantPhone\",\"optional\":true},{\"control_type\":\"text\",\"label\":\"Birthdate\",\"type\":\"string\",\"name\":\"Birthdate\",\"optional\":true},{\"control_type\":\"text\",\"label\":\"Fax\",\"type\":\"string\",\"name\":\"Fax\",\"optional\":true},{\"control_type\":\"text\",\"label\":\"Phone\",\"type\":\"string\",\"name\":\"Phone\",\"optional\":true},{\"control_type\":\"text\",\"label\":\"Description\",\"type\":\"string\",\"name\":\"Description\",\"optional\":true},{\"control_type\":\"text\",\"label\":\"Contact source\",\"type\":\"string\",\"name\":\"ContactSource\",\"optional\":true},{\"control_type\":\"text\",\"label\":\"Jigsaw\",\"type\":\"string\",\"name\":\"Jigsaw\",\"optional\":true},{\"control_type\":\"text\",\"label\":\"Department\",\"type\":\"string\",\"name\":\"Department\",\"optional\":true},{\"control_type\":\"text\",\"label\":\"Email bounced date\",\"type\":\"string\",\"name\":\"EmailBouncedDate\",\"optional\":true},{\"control_type\":\"text\",\"label\":\"Email bounced reason\",\"type\":\"string\",\"name\":\"EmailBouncedReason\",\"optional\":true},{\"control_type\":\"text\",\"label\":\"Lead source\",\"type\":\"string\",\"name\":\"LeadSource\",\"optional\":true},{\"control_type\":\"text\",\"label\":\"Mailing geocode accuracy\",\"type\":\"string\",\"name\":\"MailingGeocodeAccuracy\",\"optional\":true},{\"control_type\":\"text\",\"label\":\"Mailing latitude\",\"type\":\"string\",\"name\":\"MailingLatitude\",\"optional\":true},{\"control_type\":\"text\",\"label\":\"Mailing longitude\",\"type\":\"string\",\"name\":\"MailingLongitude\",\"optional\":true},{\"control_type\":\"text\",\"label\":\"Mobile phone\",\"type\":\"string\",\"name\":\"MobilePhone\",\"optional\":true},{\"control_type\":\"text\",\"label\":\"Other city\",\"type\":\"string\",\"name\":\"OtherCity\",\"optional\":true},{\"control_type\":\"text\",\"label\":\"Other country\",\"type\":\"string\",\"name\":\"OtherCountry\",\"optional\":true},{\"control_type\":\"text\",\"label\":\"Other geocode accuracy\",\"type\":\"string\",\"name\":\"OtherGeocodeAccuracy\",\"optional\":true},{\"control_type\":\"text\",\"label\":\"Other latitude\",\"type\":\"string\",\"name\":\"OtherLatitude\",\"optional\":true},{\"control_type\":\"text\",\"label\":\"Other longitude\",\"type\":\"string\",\"name\":\"OtherLongitude\",\"optional\":true},{\"control_type\":\"text\",\"label\":\"Other phone\",\"type\":\"string\",\"name\":\"OtherPhone\",\"optional\":true},{\"control_type\":\"text\",\"label\":\"Other state\",\"type\":\"string\",\"name\":\"OtherState\",\"optional\":true},{\"control_type\":\"text\",\"label\":\"Other street\",\"type\":\"string\",\"name\":\"OtherStreet\",\"optional\":true},{\"control_type\":\"text\",\"label\":\"Other postal code\",\"type\":\"string\",\"name\":\"OtherPostalCode\",\"optional\":true},{\"control_type\":\"text\",\"label\":\"Owner ID\",\"type\":\"string\",\"name\":\"OwnerId\",\"optional\":true},{\"control_type\":\"text\",\"label\":\"Individual ID\",\"type\":\"string\",\"name\":\"IndividualId\",\"optional\":true},{\"control_type\":\"text\",\"label\":\"Reports to ID\",\"type\":\"string\",\"name\":\"ReportsToId\",\"optional\":true},{\"control_type\":\"text\",\"label\":\"Salutation\",\"type\":\"string\",\"name\":\"Salutation\",\"optional\":true},{\"control_type\":\"text\",\"label\":\"Title\",\"type\":\"string\",\"name\":\"Title\",\"optional\":true}]"
      },
      "response": {
        "content_type": "json",
        "responses": [
          {
            "name": "Success",
            "http_status_code": "201",
            "body_schema": "[{\"control_type\":\"text\",\"label\":\"ID\",\"type\":\"string\",\"name\":\"id\"},{\"control_type\":\"text\",\"label\":\"Status\",\"type\":\"string\",\"name\":\"status\"}]"
          },
          {
            "name": "Error",
            "http_status_code": "400",
            "body_schema": "[{\"name\":\"error\",\"type\":\"string\",\"optional\":false,\"control_type\":\"text\",\"label\":\"Error\"}]"
          }
        ]
      }
    },
    "extended_output_schema": [
      {
        "label": "Context",
        "name": "context",
        "properties": [
          {
            "control_type": "text",
            "label": "Calling IP address",
            "optional": true,
            "type": "string",
            "name": "calling_ip"
          },
          {
            "properties": [
              {
                "control_type": "integer",
                "label": "Access profile ID",
                "parse_output": "integer_conversion",
                "optional": true,
                "type": "integer",
                "name": "id"
              },
              {
                "control_type": "text",
                "label": "Access profile name",
                "optional": true,
                "type": "string",
                "name": "name"
              },
              {
                "control_type": "text",
                "label": "Access profile authentication type",
                "optional": true,
                "type": "string",
                "name": "type"
              }
            ],
            "label": "Access profile",
            "type": "object",
            "name": "access_profile"
          },
          {
            "properties": [
              {
                "control_type": "text",
                "label": "API client ID",
                "optional": true,
                "type": "string",
                "name": "id"
              },
              {
                "control_type": "text",
                "label": "API client name",
                "optional": true,
                "type": "string",
                "name": "name"
              }
            ],
            "label": "API client",
            "type": "object",
            "name": "client"
          },
          {
            "properties": [
              {
                "control_type": "integer",
                "label": "Issued At",
                "render_input": "date_time_conversion",
                "parse_output": "date_time_conversion",
                "optional": true,
                "type": "date_time",
                "name": "iat"
              },
              {
                "control_type": "integer",
                "label": "Not Before",
                "render_input": "date_time_conversion",
                "parse_output": "date_time_conversion",
                "optional": true,
                "type": "date_time",
                "name": "nbf"
              },
              {
                "control_type": "integer",
                "label": "Expiration Time",
                "render_input": "date_time_conversion",
                "parse_output": "date_time_conversion",
                "optional": true,
                "type": "date_time",
                "name": "exp"
              },
              {
                "control_type": "text",
                "label": "Audience",
                "optional": true,
                "type": "string",
                "name": "aud"
              },
              {
                "control_type": "text",
                "label": "JWT ID",
                "optional": true,
                "type": "string",
                "name": "jti"
              },
              {
                "control_type": "text",
                "label": "Issuer",
                "optional": true,
                "type": "string",
                "name": "iss"
              }
            ],
            "label": "JWT claims",
            "type": "object",
            "name": "jwt_payload"
          },
          {
            "properties": [
              {
                "properties": [
                  {
                    "control_type": "checkbox",
                    "label": "Active",
                    "render_input": "boolean_conversion",
                    "parse_output": "boolean_conversion",
                    "optional": true,
                    "toggle_hint": "Select from option list",
                    "toggle_field": {
                      "label": "Active",
                      "control_type": "text",
                      "toggle_hint": "Use custom value",
                      "optional": true,
                      "type": "boolean",
                      "name": "active"
                    },
                    "type": "boolean",
                    "name": "active"
                  },
                  {
                    "control_type": "text",
                    "label": "Scope",
                    "optional": true,
                    "type": "string",
                    "name": "scope"
                  },
                  {
                    "control_type": "text",
                    "label": "Client ID",
                    "optional": true,
                    "type": "string",
                    "name": "client_id"
                  },
                  {
                    "control_type": "text",
                    "label": "Username",
                    "optional": true,
                    "type": "string",
                    "name": "username"
                  },
                  {
                    "control_type": "text",
                    "label": "Token type",
                    "optional": true,
                    "type": "string",
                    "name": "token_type"
                  },
                  {
                    "control_type": "text",
                    "label": "Exp",
                    "optional": true,
                    "type": "string",
                    "name": "exp"
                  }
                ],
                "label": "Response Body",
                "type": "object",
                "name": "payload"
              }
            ],
            "label": "Token introspection",
            "type": "object",
            "name": "introspect"
          }
        ],
        "type": "object"
      },
      {
        "label": "Request parameters",
        "name": "request",
        "properties": [
          {
            "control_type": "text",
            "label": "ID",
            "type": "string",
            "name": "id",
            "optional": true
          },
          {
            "control_type": "text",
            "label": "Last name",
            "type": "string",
            "name": "LastName"
          },
          {
            "control_type": "text",
            "label": "Account ID",
            "type": "string",
            "name": "AccountId",
            "optional": true
          },
          {
            "control_type": "text",
            "label": "Email",
            "type": "string",
            "name": "Email",
            "optional": true
          },
          {
            "control_type": "text",
            "label": "First name",
            "type": "string",
            "name": "FirstName",
            "optional": true
          },
          {
            "control_type": "text",
            "label": "Home phone",
            "type": "string",
            "name": "HomePhone",
            "optional": true
          },
          {
            "control_type": "text",
            "label": "Mailing city",
            "type": "string",
            "name": "MailingCity",
            "optional": true
          },
          {
            "control_type": "text",
            "label": "Mailing country",
            "type": "string",
            "name": "MailingCountry",
            "optional": true
          },
          {
            "control_type": "text",
            "label": "Mailing state",
            "type": "string",
            "name": "MailingState",
            "optional": true
          },
          {
            "control_type": "text",
            "label": "Mailing street",
            "type": "string",
            "name": "MailingStreet",
            "optional": true
          },
          {
            "control_type": "text",
            "label": "Mailing postal code",
            "type": "string",
            "name": "MailingPostalCode",
            "optional": true
          },
          {
            "control_type": "text",
            "label": "Assistant name",
            "type": "string",
            "name": "AssistantName",
            "optional": true
          },
          {
            "control_type": "text",
            "label": "Assistant phone",
            "type": "string",
            "name": "AssistantPhone",
            "optional": true
          },
          {
            "control_type": "text",
            "label": "Birthdate",
            "type": "string",
            "name": "Birthdate",
            "optional": true
          },
          {
            "control_type": "text",
            "label": "Fax",
            "type": "string",
            "name": "Fax",
            "optional": true
          },
          {
            "control_type": "text",
            "label": "Phone",
            "type": "string",
            "name": "Phone",
            "optional": true
          },
          {
            "control_type": "text",
            "label": "Description",
            "type": "string",
            "name": "Description",
            "optional": true
          },
          {
            "control_type": "text",
            "label": "Contact source",
            "type": "string",
            "name": "ContactSource",
            "optional": true
          },
          {
            "control_type": "text",
            "label": "Jigsaw",
            "type": "string",
            "name": "Jigsaw",
            "optional": true
          },
          {
            "control_type": "text",
            "label": "Department",
            "type": "string",
            "name": "Department",
            "optional": true
          },
          {
            "control_type": "text",
            "label": "Email bounced date",
            "type": "string",
            "name": "EmailBouncedDate",
            "optional": true
          },
          {
            "control_type": "text",
            "label": "Email bounced reason",
            "type": "string",
            "name": "EmailBouncedReason",
            "optional": true
          },
          {
            "control_type": "text",
            "label": "Lead source",
            "type": "string",
            "name": "LeadSource",
            "optional": true
          },
          {
            "control_type": "text",
            "label": "Mailing geocode accuracy",
            "type": "string",
            "name": "MailingGeocodeAccuracy",
            "optional": true
          },
          {
            "control_type": "text",
            "label": "Mailing latitude",
            "type": "string",
            "name": "MailingLatitude",
            "optional": true
          },
          {
            "control_type": "text",
            "label": "Mailing longitude",
            "type": "string",
            "name": "MailingLongitude",
            "optional": true
          },
          {
            "control_type": "text",
            "label": "Mobile phone",
            "type": "string",
            "name": "MobilePhone",
            "optional": true
          },
          {
            "control_type": "text",
            "label": "Other city",
            "type": "string",
            "name": "OtherCity",
            "optional": true
          },
          {
            "control_type": "text",
            "label": "Other country",
            "type": "string",
            "name": "OtherCountry",
            "optional": true
          },
          {
            "control_type": "text",
            "label": "Other geocode accuracy",
            "type": "string",
            "name": "OtherGeocodeAccuracy",
            "optional": true
          },
          {
            "control_type": "text",
            "label": "Other latitude",
            "type": "string",
            "name": "OtherLatitude",
            "optional": true
          },
          {
            "control_type": "text",
            "label": "Other longitude",
            "type": "string",
            "name": "OtherLongitude",
            "optional": true
          },
          {
            "control_type": "text",
            "label": "Other phone",
            "type": "string",
            "name": "OtherPhone",
            "optional": true
          },
          {
            "control_type": "text",
            "label": "Other state",
            "type": "string",
            "name": "OtherState",
            "optional": true
          },
          {
            "control_type": "text",
            "label": "Other street",
            "type": "string",
            "name": "OtherStreet",
            "optional": true
          },
          {
            "control_type": "text",
            "label": "Other postal code",
            "type": "string",
            "name": "OtherPostalCode",
            "optional": true
          },
          {
            "control_type": "text",
            "label": "Owner ID",
            "type": "string",
            "name": "OwnerId",
            "optional": true
          },
          {
            "control_type": "text",
            "label": "Individual ID",
            "type": "string",
            "name": "IndividualId",
            "optional": true
          },
          {
            "control_type": "text",
            "label": "Reports to ID",
            "type": "string",
            "name": "ReportsToId",
            "optional": true
          },
          {
            "control_type": "text",
            "label": "Salutation",
            "type": "string",
            "name": "Salutation",
            "optional": true
          },
          {
            "control_type": "text",
            "label": "Title",
            "type": "string",
            "name": "Title",
            "optional": true
          }
        ],
        "type": "object"
      }
    ],
    "block": [
      {
        "number": 1,
        "keyword": "try",
        "input": {
        },
        "block": [
          {
            "number": 2,
            "provider": "salesforce",
            "name": "upsert_sobject",
            "as": "5a0952a3",
            "keyword": "action",
            "dynamicPickListSelection": {
              "sobject_name": "Contact",
              "query_field.primary_key": [
                {
                  "label": "Contact ID",
                  "value": "Id"
                }
              ]
            },
            "toggleCfg": {
              "ContactSource": false,
              "LeadSource": false,
              "MailingGeocodeAccuracy": false,
              "OtherGeocodeAccuracy": false,
              "Salutation": false
            },
            "input": {
              "sobject_name": "Contact",
              "query_field": {
                "primary_key": "Id"
              },
              "Id": "=_dp('{\"pill_type\":\"output\",\"provider\":\"workato_api_platform\",\"line\":\"058c38c2\",\"path\":[\"request\",\"id\"]}').present? ? _dp('{\"pill_type\":\"output\",\"provider\":\"workato_api_platform\",\"line\":\"058c38c2\",\"path\":[\"request\",\"id\"]}') : skip",
              "LastName": "#{_dp('{\"pill_type\":\"output\",\"provider\":\"workato_api_platform\",\"line\":\"058c38c2\",\"path\":[\"request\",\"LastName\"]}')}",
              "AccountId": "=_dp('{\"pill_type\":\"output\",\"provider\":\"workato_api_platform\",\"line\":\"058c38c2\",\"path\":[\"request\",\"AccountId\"]}').present? ? _dp('{\"pill_type\":\"output\",\"provider\":\"workato_api_platform\",\"line\":\"058c38c2\",\"path\":[\"request\",\"AccountId\"]}') : skip",
              "AssistantName": "=_dp('{\"pill_type\":\"output\",\"provider\":\"workato_api_platform\",\"line\":\"058c38c2\",\"path\":[\"request\",\"AssistantName\"]}').present? ? _dp('{\"pill_type\":\"output\",\"provider\":\"workato_api_platform\",\"line\":\"058c38c2\",\"path\":[\"request\",\"AssistantName\"]}') : skip",
              "AssistantPhone": "=_dp('{\"pill_type\":\"output\",\"provider\":\"workato_api_platform\",\"line\":\"058c38c2\",\"path\":[\"request\",\"AssistantPhone\"]}').present? ? _dp('{\"pill_type\":\"output\",\"provider\":\"workato_api_platform\",\"line\":\"058c38c2\",\"path\":[\"request\",\"AssistantPhone\"]}') : skip",
              "Birthdate": "=_dp('{\"pill_type\":\"output\",\"provider\":\"workato_api_platform\",\"line\":\"058c38c2\",\"path\":[\"request\",\"Birthdate\"]}').present? ? _dp('{\"pill_type\":\"output\",\"provider\":\"workato_api_platform\",\"line\":\"058c38c2\",\"path\":[\"request\",\"Birthdate\"]}') : skip",
              "Fax": "=_dp('{\"pill_type\":\"output\",\"provider\":\"workato_api_platform\",\"line\":\"058c38c2\",\"path\":[\"request\",\"Fax\"]}').present? ? _dp('{\"pill_type\":\"output\",\"provider\":\"workato_api_platform\",\"line\":\"058c38c2\",\"path\":[\"request\",\"Fax\"]}') : skip",
              "Phone": "=_dp('{\"pill_type\":\"output\",\"provider\":\"workato_api_platform\",\"line\":\"058c38c2\",\"path\":[\"request\",\"Phone\"]}').present? ? _dp('{\"pill_type\":\"output\",\"provider\":\"workato_api_platform\",\"line\":\"058c38c2\",\"path\":[\"request\",\"Phone\"]}') : skip",
              "Description": "=_dp('{\"pill_type\":\"output\",\"provider\":\"workato_api_platform\",\"line\":\"058c38c2\",\"path\":[\"request\",\"Description\"]}').present? ? _dp('{\"pill_type\":\"output\",\"provider\":\"workato_api_platform\",\"line\":\"058c38c2\",\"path\":[\"request\",\"Description\"]}') : skip",
              "Jigsaw": "=_dp('{\"pill_type\":\"output\",\"provider\":\"workato_api_platform\",\"line\":\"058c38c2\",\"path\":[\"request\",\"Jigsaw\"]}').present? ? _dp('{\"pill_type\":\"output\",\"provider\":\"workato_api_platform\",\"line\":\"058c38c2\",\"path\":[\"request\",\"Jigsaw\"]}') : skip",
              "Department": "=_dp('{\"pill_type\":\"output\",\"provider\":\"workato_api_platform\",\"line\":\"058c38c2\",\"path\":[\"request\",\"Department\"]}').present? ? _dp('{\"pill_type\":\"output\",\"provider\":\"workato_api_platform\",\"line\":\"058c38c2\",\"path\":[\"request\",\"Department\"]}') : skip",
              "Email": "=_dp('{\"pill_type\":\"output\",\"provider\":\"workato_api_platform\",\"line\":\"058c38c2\",\"path\":[\"request\",\"Email\"]}').present? ? _dp('{\"pill_type\":\"output\",\"provider\":\"workato_api_platform\",\"line\":\"058c38c2\",\"path\":[\"request\",\"Email\"]}') : skip",
              "EmailBouncedDate": "=_dp('{\"pill_type\":\"output\",\"provider\":\"workato_api_platform\",\"line\":\"058c38c2\",\"path\":[\"request\",\"EmailBouncedDate\"]}').present? ? _dp('{\"pill_type\":\"output\",\"provider\":\"workato_api_platform\",\"line\":\"058c38c2\",\"path\":[\"request\",\"EmailBouncedDate\"]}') : skip",
              "EmailBouncedReason": "=_dp('{\"pill_type\":\"output\",\"provider\":\"workato_api_platform\",\"line\":\"058c38c2\",\"path\":[\"request\",\"EmailBouncedReason\"]}').present? ? _dp('{\"pill_type\":\"output\",\"provider\":\"workato_api_platform\",\"line\":\"058c38c2\",\"path\":[\"request\",\"EmailBouncedReason\"]}') : skip",
              "FirstName": "=_dp('{\"pill_type\":\"output\",\"provider\":\"workato_api_platform\",\"line\":\"058c38c2\",\"path\":[\"request\",\"FirstName\"]}').present? ? _dp('{\"pill_type\":\"output\",\"provider\":\"workato_api_platform\",\"line\":\"058c38c2\",\"path\":[\"request\",\"FirstName\"]}') : skip",
              "HomePhone": "=_dp('{\"pill_type\":\"output\",\"provider\":\"workato_api_platform\",\"line\":\"058c38c2\",\"path\":[\"request\",\"HomePhone\"]}').present? ? _dp('{\"pill_type\":\"output\",\"provider\":\"workato_api_platform\",\"line\":\"058c38c2\",\"path\":[\"request\",\"HomePhone\"]}') : skip",
              "IndividualId": "=_dp('{\"pill_type\":\"output\",\"provider\":\"workato_api_platform\",\"line\":\"058c38c2\",\"path\":[\"request\",\"IndividualId\"]}').present? ? _dp('{\"pill_type\":\"output\",\"provider\":\"workato_api_platform\",\"line\":\"058c38c2\",\"path\":[\"request\",\"IndividualId\"]}') : skip",
              "MailingCity": "=_dp('{\"pill_type\":\"output\",\"provider\":\"workato_api_platform\",\"line\":\"058c38c2\",\"path\":[\"request\",\"MailingCity\"]}').present? ? _dp('{\"pill_type\":\"output\",\"provider\":\"workato_api_platform\",\"line\":\"058c38c2\",\"path\":[\"request\",\"MailingCity\"]}') : skip",
              "MailingCountry": "=_dp('{\"pill_type\":\"output\",\"provider\":\"workato_api_platform\",\"line\":\"058c38c2\",\"path\":[\"request\",\"MailingCountry\"]}').present? ? _dp('{\"pill_type\":\"output\",\"provider\":\"workato_api_platform\",\"line\":\"058c38c2\",\"path\":[\"request\",\"MailingCountry\"]}') : skip",
              "MailingLatitude": "=_dp('{\"pill_type\":\"output\",\"provider\":\"workato_api_platform\",\"line\":\"058c38c2\",\"path\":[\"request\",\"MailingLatitude\"]}').present? ? _dp('{\"pill_type\":\"output\",\"provider\":\"workato_api_platform\",\"line\":\"058c38c2\",\"path\":[\"request\",\"MailingLatitude\"]}') : skip",
              "MailingLongitude": "=_dp('{\"pill_type\":\"output\",\"provider\":\"workato_api_platform\",\"line\":\"058c38c2\",\"path\":[\"request\",\"MailingLongitude\"]}').present? ? _dp('{\"pill_type\":\"output\",\"provider\":\"workato_api_platform\",\"line\":\"058c38c2\",\"path\":[\"request\",\"MailingLongitude\"]}') : skip",
              "MailingState": "=_dp('{\"pill_type\":\"output\",\"provider\":\"workato_api_platform\",\"line\":\"058c38c2\",\"path\":[\"request\",\"MailingState\"]}').present? ? _dp('{\"pill_type\":\"output\",\"provider\":\"workato_api_platform\",\"line\":\"058c38c2\",\"path\":[\"request\",\"MailingState\"]}') : skip",
              "MailingStreet": "=_dp('{\"pill_type\":\"output\",\"provider\":\"workato_api_platform\",\"line\":\"058c38c2\",\"path\":[\"request\",\"MailingStreet\"]}').present? ? _dp('{\"pill_type\":\"output\",\"provider\":\"workato_api_platform\",\"line\":\"058c38c2\",\"path\":[\"request\",\"MailingStreet\"]}') : skip",
              "MailingPostalCode": "=_dp('{\"pill_type\":\"output\",\"provider\":\"workato_api_platform\",\"line\":\"058c38c2\",\"path\":[\"request\",\"MailingPostalCode\"]}').present? ? _dp('{\"pill_type\":\"output\",\"provider\":\"workato_api_platform\",\"line\":\"058c38c2\",\"path\":[\"request\",\"MailingPostalCode\"]}') : skip",
              "MobilePhone": "=_dp('{\"pill_type\":\"output\",\"provider\":\"workato_api_platform\",\"line\":\"058c38c2\",\"path\":[\"request\",\"MobilePhone\"]}').present? ? _dp('{\"pill_type\":\"output\",\"provider\":\"workato_api_platform\",\"line\":\"058c38c2\",\"path\":[\"request\",\"MobilePhone\"]}') : skip",
              "OtherCity": "=_dp('{\"pill_type\":\"output\",\"provider\":\"workato_api_platform\",\"line\":\"058c38c2\",\"path\":[\"request\",\"OtherCity\"]}').present? ? _dp('{\"pill_type\":\"output\",\"provider\":\"workato_api_platform\",\"line\":\"058c38c2\",\"path\":[\"request\",\"OtherCity\"]}') : skip",
              "OtherCountry": "=_dp('{\"pill_type\":\"output\",\"provider\":\"workato_api_platform\",\"line\":\"058c38c2\",\"path\":[\"request\",\"OtherCountry\"]}').present? ? _dp('{\"pill_type\":\"output\",\"provider\":\"workato_api_platform\",\"line\":\"058c38c2\",\"path\":[\"request\",\"OtherCountry\"]}') : skip",
              "OtherLatitude": "=_dp('{\"pill_type\":\"output\",\"provider\":\"workato_api_platform\",\"line\":\"058c38c2\",\"path\":[\"request\",\"OtherLatitude\"]}').present? ? _dp('{\"pill_type\":\"output\",\"provider\":\"workato_api_platform\",\"line\":\"058c38c2\",\"path\":[\"request\",\"OtherLatitude\"]}') : skip",
              "OtherLongitude": "=_dp('{\"pill_type\":\"output\",\"provider\":\"workato_api_platform\",\"line\":\"058c38c2\",\"path\":[\"request\",\"OtherLongitude\"]}').present? ? _dp('{\"pill_type\":\"output\",\"provider\":\"workato_api_platform\",\"line\":\"058c38c2\",\"path\":[\"request\",\"OtherLongitude\"]}') : skip",
              "OtherPhone": "=_dp('{\"pill_type\":\"output\",\"provider\":\"workato_api_platform\",\"line\":\"058c38c2\",\"path\":[\"request\",\"OtherPhone\"]}').present? ? _dp('{\"pill_type\":\"output\",\"provider\":\"workato_api_platform\",\"line\":\"058c38c2\",\"path\":[\"request\",\"OtherPhone\"]}') : skip",
              "OtherState": "=_dp('{\"pill_type\":\"output\",\"provider\":\"workato_api_platform\",\"line\":\"058c38c2\",\"path\":[\"request\",\"OtherState\"]}').present? ? _dp('{\"pill_type\":\"output\",\"provider\":\"workato_api_platform\",\"line\":\"058c38c2\",\"path\":[\"request\",\"OtherState\"]}') : skip",
              "OtherStreet": "=_dp('{\"pill_type\":\"output\",\"provider\":\"workato_api_platform\",\"line\":\"058c38c2\",\"path\":[\"request\",\"OtherStreet\"]}').present? ? _dp('{\"pill_type\":\"output\",\"provider\":\"workato_api_platform\",\"line\":\"058c38c2\",\"path\":[\"request\",\"OtherStreet\"]}') : skip",
              "OtherPostalCode": "=_dp('{\"pill_type\":\"output\",\"provider\":\"workato_api_platform\",\"line\":\"058c38c2\",\"path\":[\"request\",\"OtherPostalCode\"]}').present? ? _dp('{\"pill_type\":\"output\",\"provider\":\"workato_api_platform\",\"line\":\"058c38c2\",\"path\":[\"request\",\"OtherPostalCode\"]}') : skip",
              "OwnerId": "=_dp('{\"pill_type\":\"output\",\"provider\":\"workato_api_platform\",\"line\":\"058c38c2\",\"path\":[\"request\",\"OwnerId\"]}').present? ? _dp('{\"pill_type\":\"output\",\"provider\":\"workato_api_platform\",\"line\":\"058c38c2\",\"path\":[\"request\",\"OwnerId\"]}') : skip",
              "ReportsToId": "=_dp('{\"pill_type\":\"output\",\"provider\":\"workato_api_platform\",\"line\":\"058c38c2\",\"path\":[\"request\",\"ReportsToId\"]}').present? ? _dp('{\"pill_type\":\"output\",\"provider\":\"workato_api_platform\",\"line\":\"058c38c2\",\"path\":[\"request\",\"ReportsToId\"]}') : skip",
              "Title": "=_dp('{\"pill_type\":\"output\",\"provider\":\"workato_api_platform\",\"line\":\"058c38c2\",\"path\":[\"request\",\"Title\"]}').present? ? _dp('{\"pill_type\":\"output\",\"provider\":\"workato_api_platform\",\"line\":\"058c38c2\",\"path\":[\"request\",\"Title\"]}') : skip",
              "Salutation": "=_dp('{\"pill_type\":\"output\",\"provider\":\"workato_api_platform\",\"line\":\"058c38c2\",\"path\":[\"request\",\"Salutation\"]}').present? ? _dp('{\"pill_type\":\"output\",\"provider\":\"workato_api_platform\",\"line\":\"058c38c2\",\"path\":[\"request\",\"Salutation\"]}') : skip",
              "OtherGeocodeAccuracy": "=_dp('{\"pill_type\":\"output\",\"provider\":\"workato_api_platform\",\"line\":\"058c38c2\",\"path\":[\"request\",\"OtherGeocodeAccuracy\"]}').present? ? _dp('{\"pill_type\":\"output\",\"provider\":\"workato_api_platform\",\"line\":\"058c38c2\",\"path\":[\"request\",\"OtherGeocodeAccuracy\"]}') : skip",
              "MailingGeocodeAccuracy": "=_dp('{\"pill_type\":\"output\",\"provider\":\"workato_api_platform\",\"line\":\"058c38c2\",\"path\":[\"request\",\"MailingGeocodeAccuracy\"]}').present? ? _dp('{\"pill_type\":\"output\",\"provider\":\"workato_api_platform\",\"line\":\"058c38c2\",\"path\":[\"request\",\"MailingGeocodeAccuracy\"]}') : skip",
              "LeadSource": "=_dp('{\"pill_type\":\"output\",\"provider\":\"workato_api_platform\",\"line\":\"058c38c2\",\"path\":[\"request\",\"LeadSource\"]}').present? ? _dp('{\"pill_type\":\"output\",\"provider\":\"workato_api_platform\",\"line\":\"058c38c2\",\"path\":[\"request\",\"LeadSource\"]}') : skip",
              "ContactSource": "=_dp('{\"pill_type\":\"output\",\"provider\":\"workato_api_platform\",\"line\":\"058c38c2\",\"path\":[\"request\",\"ContactSource\"]}').present? ? _dp('{\"pill_type\":\"output\",\"provider\":\"workato_api_platform\",\"line\":\"058c38c2\",\"path\":[\"request\",\"ContactSource\"]}') : skip"
            },
            "extended_input_schema": [
              {
                "control_type": "text",
                "custom": false,
                "label": "Last Name",
                "name": "LastName",
                "type": "string",
                "sfdc_createable": true,
                "sfdc_updateable": true
              },
              {
                "control_type": "text",
                "custom": false,
                "hint": "Search for  where Contact ID has this value. If a record already exists, it will be updated. Otherwise, a new record will be created",
                "label": "Contact ID",
                "name": "Id",
                "optional": true,
                "sticky": true,
                "type": "string",
                "sfdc_createable": false,
                "sfdc_updateable": false
              },
              {
                "control_type": "text",
                "custom": false,
                "label": "Account ID",
                "name": "AccountId",
                "optional": true,
                "type": "string",
                "sfdc_createable": true,
                "sfdc_updateable": true
              },
              {
                "control_type": "text",
                "custom": false,
                "label": "Assistant's Name",
                "name": "AssistantName",
                "optional": true,
                "type": "string",
                "sfdc_createable": true,
                "sfdc_updateable": true
              },
              {
                "control_type": "phone",
                "custom": false,
                "label": "Asst. Phone",
                "name": "AssistantPhone",
                "optional": true,
                "type": "string",
                "sfdc_createable": true,
                "sfdc_updateable": true
              },
              {
                "control_type": "date",
                "custom": false,
                "label": "Birthdate",
                "name": "Birthdate",
                "optional": true,
                "parse_output": "parse_iso8601_date",
                "type": "date_time",
                "render_input": "render_iso8601_date",
                "sfdc_createable": true,
                "sfdc_updateable": true
              },
              {
                "control_type": "phone",
                "custom": false,
                "label": "Business Fax",
                "name": "Fax",
                "optional": true,
                "type": "string",
                "sfdc_createable": true,
                "sfdc_updateable": true
              },
              {
                "control_type": "phone",
                "custom": false,
                "label": "Business Phone",
                "name": "Phone",
                "optional": true,
                "type": "string",
                "sfdc_createable": true,
                "sfdc_updateable": true
              },
              {
                "control_type": "select",
                "custom": false,
                "label": "Clean Status",
                "name": "CleanStatus",
                "optional": true,
                "pick_list": "sobject_field_values_list",
                "pick_list_params": {
                  "sobject_name": "\"Contact\"",
                  "field_name": "\"CleanStatus\""
                },
                "toggle_field": {
                  "control_type": "text",
                  "label": "Clean Status",
                  "toggle_hint": "Enter custom value",
                  "optional": true,
                  "custom": false,
                  "sfdc_createable": true,
                  "sfdc_updateable": true,
                  "type": "string",
                  "name": "CleanStatus"
                },
                "toggle_hint": "Select from list",
                "type": "string",
                "sfdc_createable": true,
                "sfdc_updateable": true
              },
              {
                "control_type": "text-area",
                "custom": false,
                "label": "Contact Description",
                "name": "Description",
                "optional": true,
                "type": "string",
                "sfdc_createable": true,
                "sfdc_updateable": true
              },
              {
                "control_type": "select",
                "custom": false,
                "label": "Creation Source",
                "name": "ContactSource",
                "optional": true,
                "pick_list": "sobject_field_values_list",
                "pick_list_params": {
                  "sobject_name": "\"Contact\"",
                  "field_name": "\"ContactSource\""
                },
                "toggle_field": {
                  "control_type": "text",
                  "label": "Creation Source",
                  "toggle_hint": "Enter custom value",
                  "optional": true,
                  "custom": false,
                  "sfdc_createable": true,
                  "sfdc_updateable": true,
                  "type": "string",
                  "name": "ContactSource"
                },
                "toggle_hint": "Select from list",
                "type": "string",
                "sfdc_createable": true,
                "sfdc_updateable": true
              },
              {
                "control_type": "text",
                "custom": false,
                "label": "Data.com Key",
                "name": "Jigsaw",
                "optional": true,
                "type": "string",
                "sfdc_createable": true,
                "sfdc_updateable": true
              },
              {
                "control_type": "text",
                "custom": false,
                "label": "Department",
                "name": "Department",
                "optional": true,
                "type": "string",
                "sfdc_createable": true,
                "sfdc_updateable": true
              },
              {
                "control_type": "text",
                "custom": false,
                "label": "Email",
                "name": "Email",
                "optional": true,
                "type": "string",
                "sfdc_createable": true,
                "sfdc_updateable": true
              },
              {
                "control_type": "date_time",
                "custom": false,
                "label": "Email Bounced Date",
                "name": "EmailBouncedDate",
                "optional": true,
                "parse_output": "parse_iso8601_timestamp",
                "type": "date_time",
                "render_input": "render_iso8601_timestamp",
                "sfdc_createable": true,
                "sfdc_updateable": true
              },
              {
                "control_type": "text",
                "custom": false,
                "label": "Email Bounced Reason",
                "name": "EmailBouncedReason",
                "optional": true,
                "type": "string",
                "sfdc_createable": true,
                "sfdc_updateable": true
              },
              {
                "control_type": "text",
                "custom": false,
                "label": "First Name",
                "name": "FirstName",
                "optional": true,
                "type": "string",
                "sfdc_createable": true,
                "sfdc_updateable": true
              },
              {
                "control_type": "phone",
                "custom": false,
                "label": "Home Phone",
                "name": "HomePhone",
                "optional": true,
                "type": "string",
                "sfdc_createable": true,
                "sfdc_updateable": true
              },
              {
                "control_type": "text",
                "custom": false,
                "label": "Individual ID",
                "name": "IndividualId",
                "optional": true,
                "type": "string",
                "sfdc_createable": true,
                "sfdc_updateable": true
              },
              {
                "control_type": "select",
                "custom": false,
                "label": "Lead Source",
                "name": "LeadSource",
                "optional": true,
                "pick_list": "sobject_field_values_list",
                "pick_list_params": {
                  "sobject_name": "\"Contact\"",
                  "field_name": "\"LeadSource\""
                },
                "toggle_field": {
                  "control_type": "text",
                  "label": "Lead Source",
                  "toggle_hint": "Enter custom value",
                  "optional": true,
                  "custom": false,
                  "sfdc_createable": true,
                  "sfdc_updateable": true,
                  "type": "string",
                  "name": "LeadSource"
                },
                "toggle_hint": "Select from list",
                "type": "string",
                "sfdc_createable": true,
                "sfdc_updateable": true
              },
              {
                "control_type": "text",
                "custom": false,
                "label": "Mailing City",
                "name": "MailingCity",
                "optional": true,
                "type": "string",
                "sfdc_createable": true,
                "sfdc_updateable": true
              },
              {
                "control_type": "text",
                "custom": false,
                "label": "Mailing Country",
                "name": "MailingCountry",
                "optional": true,
                "type": "string",
                "sfdc_createable": true,
                "sfdc_updateable": true
              },
              {
                "control_type": "select",
                "custom": false,
                "label": "Mailing Country Code",
                "name": "MailingCountryCode",
                "optional": true,
                "pick_list": "sobject_field_values_list",
                "pick_list_params": {
                  "sobject_name": "\"Contact\"",
                  "field_name": "\"MailingCountryCode\""
                },
                "toggle_field": {
                  "control_type": "text",
                  "label": "Mailing Country Code",
                  "toggle_hint": "Enter custom value",
                  "optional": true,
                  "custom": false,
                  "sfdc_createable": true,
                  "sfdc_updateable": true,
                  "type": "string",
                  "name": "MailingCountryCode"
                },
                "toggle_hint": "Select from list",
                "type": "string",
                "sfdc_createable": true,
                "sfdc_updateable": true
              },
              {
                "control_type": "select",
                "custom": false,
                "label": "Mailing Geocode Accuracy",
                "name": "MailingGeocodeAccuracy",
                "optional": true,
                "pick_list": "sobject_field_values_list",
                "pick_list_params": {
                  "sobject_name": "\"Contact\"",
                  "field_name": "\"MailingGeocodeAccuracy\""
                },
                "toggle_field": {
                  "control_type": "text",
                  "label": "Mailing Geocode Accuracy",
                  "toggle_hint": "Enter custom value",
                  "optional": true,
                  "custom": false,
                  "sfdc_createable": true,
                  "sfdc_updateable": true,
                  "type": "string",
                  "name": "MailingGeocodeAccuracy"
                },
                "toggle_hint": "Select from list",
                "type": "string",
                "sfdc_createable": true,
                "sfdc_updateable": true
              },
              {
                "control_type": "number",
                "custom": false,
                "label": "Mailing Latitude",
                "name": "MailingLatitude",
                "optional": true,
                "parse_output": "float_conversion",
                "type": "number",
                "sfdc_createable": true,
                "sfdc_updateable": true
              },
              {
                "control_type": "number",
                "custom": false,
                "label": "Mailing Longitude",
                "name": "MailingLongitude",
                "optional": true,
                "parse_output": "float_conversion",
                "type": "number",
                "sfdc_createable": true,
                "sfdc_updateable": true
              },
              {
                "control_type": "text",
                "custom": false,
                "label": "Mailing State/Province",
                "name": "MailingState",
                "optional": true,
                "type": "string",
                "sfdc_createable": true,
                "sfdc_updateable": true
              },
              {
                "control_type": "select",
                "custom": false,
                "label": "Mailing State/Province Code",
                "name": "MailingStateCode",
                "optional": true,
                "pick_list": "sobject_field_values_list",
                "pick_list_params": {
                  "sobject_name": "\"Contact\"",
                  "field_name": "\"MailingStateCode\""
                },
                "toggle_field": {
                  "control_type": "text",
                  "label": "Mailing State/Province Code",
                  "toggle_hint": "Enter custom value",
                  "optional": true,
                  "custom": false,
                  "sfdc_createable": true,
                  "sfdc_updateable": true,
                  "type": "string",
                  "name": "MailingStateCode"
                },
                "toggle_hint": "Select from list",
                "type": "string",
                "sfdc_createable": true,
                "sfdc_updateable": true
              },
              {
                "control_type": "text-area",
                "custom": false,
                "label": "Mailing Street",
                "name": "MailingStreet",
                "optional": true,
                "type": "string",
                "sfdc_createable": true,
                "sfdc_updateable": true
              },
              {
                "control_type": "text",
                "custom": false,
                "label": "Mailing Zip/Postal Code",
                "name": "MailingPostalCode",
                "optional": true,
                "type": "string",
                "sfdc_createable": true,
                "sfdc_updateable": true
              },
              {
                "control_type": "phone",
                "custom": false,
                "label": "Mobile Phone",
                "name": "MobilePhone",
                "optional": true,
                "type": "string",
                "sfdc_createable": true,
                "sfdc_updateable": true
              },
              {
                "control_type": "text",
                "custom": false,
                "label": "Other City",
                "name": "OtherCity",
                "optional": true,
                "type": "string",
                "sfdc_createable": true,
                "sfdc_updateable": true
              },
              {
                "control_type": "text",
                "custom": false,
                "label": "Other Country",
                "name": "OtherCountry",
                "optional": true,
                "type": "string",
                "sfdc_createable": true,
                "sfdc_updateable": true
              },
              {
                "control_type": "select",
                "custom": false,
                "label": "Other Country Code",
                "name": "OtherCountryCode",
                "optional": true,
                "pick_list": "sobject_field_values_list",
                "pick_list_params": {
                  "sobject_name": "\"Contact\"",
                  "field_name": "\"OtherCountryCode\""
                },
                "toggle_field": {
                  "control_type": "text",
                  "label": "Other Country Code",
                  "toggle_hint": "Enter custom value",
                  "optional": true,
                  "custom": false,
                  "sfdc_createable": true,
                  "sfdc_updateable": true,
                  "type": "string",
                  "name": "OtherCountryCode"
                },
                "toggle_hint": "Select from list",
                "type": "string",
                "sfdc_createable": true,
                "sfdc_updateable": true
              },
              {
                "control_type": "select",
                "custom": false,
                "label": "Other Geocode Accuracy",
                "name": "OtherGeocodeAccuracy",
                "optional": true,
                "pick_list": "sobject_field_values_list",
                "pick_list_params": {
                  "sobject_name": "\"Contact\"",
                  "field_name": "\"OtherGeocodeAccuracy\""
                },
                "toggle_field": {
                  "control_type": "text",
                  "label": "Other Geocode Accuracy",
                  "toggle_hint": "Enter custom value",
                  "optional": true,
                  "custom": false,
                  "sfdc_createable": true,
                  "sfdc_updateable": true,
                  "type": "string",
                  "name": "OtherGeocodeAccuracy"
                },
                "toggle_hint": "Select from list",
                "type": "string",
                "sfdc_createable": true,
                "sfdc_updateable": true
              },
              {
                "control_type": "number",
                "custom": false,
                "label": "Other Latitude",
                "name": "OtherLatitude",
                "optional": true,
                "parse_output": "float_conversion",
                "type": "number",
                "sfdc_createable": true,
                "sfdc_updateable": true
              },
              {
                "control_type": "number",
                "custom": false,
                "label": "Other Longitude",
                "name": "OtherLongitude",
                "optional": true,
                "parse_output": "float_conversion",
                "type": "number",
                "sfdc_createable": true,
                "sfdc_updateable": true
              },
              {
                "control_type": "phone",
                "custom": false,
                "label": "Other Phone",
                "name": "OtherPhone",
                "optional": true,
                "type": "string",
                "sfdc_createable": true,
                "sfdc_updateable": true
              },
              {
                "control_type": "text",
                "custom": false,
                "label": "Other State/Province",
                "name": "OtherState",
                "optional": true,
                "type": "string",
                "sfdc_createable": true,
                "sfdc_updateable": true
              },
              {
                "control_type": "select",
                "custom": false,
                "label": "Other State/Province Code",
                "name": "OtherStateCode",
                "optional": true,
                "pick_list": "sobject_field_values_list",
                "pick_list_params": {
                  "sobject_name": "\"Contact\"",
                  "field_name": "\"OtherStateCode\""
                },
                "toggle_field": {
                  "control_type": "text",
                  "label": "Other State/Province Code",
                  "toggle_hint": "Enter custom value",
                  "optional": true,
                  "custom": false,
                  "sfdc_createable": true,
                  "sfdc_updateable": true,
                  "type": "string",
                  "name": "OtherStateCode"
                },
                "toggle_hint": "Select from list",
                "type": "string",
                "sfdc_createable": true,
                "sfdc_updateable": true
              },
              {
                "control_type": "text-area",
                "custom": false,
                "label": "Other Street",
                "name": "OtherStreet",
                "optional": true,
                "type": "string",
                "sfdc_createable": true,
                "sfdc_updateable": true
              },
              {
                "control_type": "text",
                "custom": false,
                "label": "Other Zip/Postal Code",
                "name": "OtherPostalCode",
                "optional": true,
                "type": "string",
                "sfdc_createable": true,
                "sfdc_updateable": true
              },
              {
                "control_type": "text",
                "custom": false,
                "label": "Owner ID",
                "name": "OwnerId",
                "optional": true,
                "type": "string",
                "sfdc_createable": true,
                "sfdc_updateable": true
              },
              {
                "control_type": "text",
                "custom": false,
                "label": "Reports To ID",
                "name": "ReportsToId",
                "optional": true,
                "type": "string",
                "sfdc_createable": true,
                "sfdc_updateable": true
              },
              {
                "control_type": "select",
                "custom": false,
                "label": "Salutation",
                "name": "Salutation",
                "optional": true,
                "pick_list": "sobject_field_values_list",
                "pick_list_params": {
                  "sobject_name": "\"Contact\"",
                  "field_name": "\"Salutation\""
                },
                "toggle_field": {
                  "control_type": "text",
                  "label": "Salutation",
                  "toggle_hint": "Enter custom value",
                  "optional": true,
                  "custom": false,
                  "sfdc_createable": true,
                  "sfdc_updateable": true,
                  "type": "string",
                  "name": "Salutation"
                },
                "toggle_hint": "Select from list",
                "type": "string",
                "sfdc_createable": true,
                "sfdc_updateable": true
              },
              {
                "control_type": "text",
                "custom": false,
                "label": "Title",
                "name": "Title",
                "optional": true,
                "type": "string",
                "sfdc_createable": true,
                "sfdc_updateable": true
              },
              {
                "control_type": "text",
                "custom": true,
                "label": "Languages",
                "name": "Languages__c",
                "optional": true,
                "type": "string",
                "sfdc_createable": true,
                "sfdc_updateable": true
              },
              {
                "control_type": "select",
                "custom": true,
                "label": "Level",
                "name": "Level__c",
                "optional": true,
                "pick_list": "sobject_field_values_list",
                "pick_list_params": {
                  "sobject_name": "\"Contact\"",
                  "field_name": "\"Level__c\""
                },
                "toggle_field": {
                  "control_type": "text",
                  "label": "Level",
                  "toggle_hint": "Enter custom value",
                  "optional": true,
                  "custom": true,
                  "sfdc_createable": true,
                  "sfdc_updateable": true,
                  "type": "string",
                  "name": "Level__c"
                },
                "toggle_hint": "Select from list",
                "type": "string",
                "sfdc_createable": true,
                "sfdc_updateable": true
              }
            ],
            "visible_config_fields": [
              "sobject_name",
              "query_field",
              "query_field.primary_key",
              "LastName",
              "Id",
              "AccountId",
              "AssistantName",
              "AssistantPhone",
              "Birthdate",
              "Fax",
              "Phone",
              "Description",
              "Jigsaw",
              "Department",
              "Email",
              "EmailBouncedDate",
              "EmailBouncedReason",
              "FirstName",
              "HomePhone",
              "IndividualId",
              "MailingCity",
              "MailingCountry",
              "MailingLatitude",
              "MailingLongitude",
              "MailingState",
              "MailingStreet",
              "MailingPostalCode",
              "MobilePhone",
              "OtherCity",
              "OtherCountry",
              "OtherLatitude",
              "OtherLongitude",
              "OtherPhone",
              "OtherState",
              "OtherStreet",
              "OtherPostalCode",
              "OwnerId",
              "ReportsToId",
              "Title",
              "relationship_fields",
              "ContactSource",
              "LeadSource",
              "MailingGeocodeAccuracy",
              "OtherGeocodeAccuracy",
              "Salutation"
            ],
            "uuid": "07765bc1-2afb-404f-a29c-34d7e73bc6c0"
          },
          {
            "number": 3,
            "as": "e110b724",
            "keyword": "catch",
            "input": {
              "max_retry_count": "0",
              "retry_interval": "2"
            },
            "block": [
              {
                "number": 4,
                "provider": "workato_api_platform",
                "name": "return_response",
                "as": "b92d1866",
                "keyword": "action",
                "input": {
                  "http_status_code": "400",
                  "response": {
                    "error": "#{_dp('{\"pill_type\":\"output\",\"provider\":\"catch\",\"line\":\"e110b724\",\"path\":[\"message\"]}')}"
                  }
                },
                "extended_output_schema": [
                  {
                    "change_on_blur": true,
                    "control_type": "select",
                    "extends_schema": true,
                    "label": "Response",
                    "name": "http_status_code",
                    "pick_list": [
                      [
                        "Success",
                        "201"
                      ],
                      [
                        "Error",
                        "400"
                      ]
                    ],
                    "type": "string"
                  },
                  {
                    "label": "Response body",
                    "name": "response",
                    "properties": [
                      {
                        "control_type": "text",
                        "label": "Error",
                        "name": "error",
                        "type": "string",
                        "optional": false
                      }
                    ],
                    "type": "object"
                  }
                ],
                "extended_input_schema": [
                  {
                    "change_on_blur": true,
                    "control_type": "select",
                    "extends_schema": true,
                    "label": "Response",
                    "name": "http_status_code",
                    "pick_list": [
                      [
                        "Success",
                        "201"
                      ],
                      [
                        "Error",
                        "400"
                      ]
                    ],
                    "type": "string"
                  },
                  {
                    "label": "Response body",
                    "name": "response",
                    "properties": [
                      {
                        "control_type": "text",
                        "label": "Error",
                        "name": "error",
                        "type": "string",
                        "optional": false
                      }
                    ],
                    "type": "object"
                  }
                ],
                "uuid": "5f1af4d7-0375-4c11-b1bf-a0ea10b22799"
              }
            ],
            "uuid": "0725a519-a96d-4bb1-bbe0-7f980a4d8970"
          }
        ],
        "uuid": "1aa1cdbb-637f-4b2e-ba4b-3da22cc23fa6"
      },
      {
        "number": 5,
        "provider": "workato_api_platform",
        "name": "return_response",
        "as": "62bb7ce9",
        "keyword": "action",
        "input": {
          "http_status_code": "201",
          "response": {
            "id": "#{_dp('{\"pill_type\":\"output\",\"provider\":\"salesforce\",\"line\":\"5a0952a3\",\"path\":[\"id\"]}')}",
            "status": "#{_dp('{\"pill_type\":\"output\",\"provider\":\"salesforce\",\"line\":\"5a0952a3\",\"path\":[\"status\"]}')}"
          }
        },
        "extended_output_schema": [
          {
            "change_on_blur": true,
            "control_type": "select",
            "extends_schema": true,
            "label": "Response",
            "name": "http_status_code",
            "pick_list": [
              [
                "Success",
                "201"
              ],
              [
                "Error",
                "400"
              ]
            ],
            "type": "string"
          },
          {
            "label": "Response body",
            "name": "response",
            "properties": [
              {
                "control_type": "text",
                "label": "ID",
                "type": "string",
                "name": "id"
              },
              {
                "control_type": "text",
                "label": "Status",
                "type": "string",
                "name": "status"
              }
            ],
            "type": "object"
          }
        ],
        "extended_input_schema": [
          {
            "change_on_blur": true,
            "control_type": "select",
            "extends_schema": true,
            "label": "Response",
            "name": "http_status_code",
            "pick_list": [
              [
                "Success",
                "201"
              ],
              [
                "Error",
                "400"
              ]
            ],
            "type": "string"
          },
          {
            "label": "Response body",
            "name": "response",
            "properties": [
              {
                "control_type": "text",
                "label": "ID",
                "type": "string",
                "name": "id"
              },
              {
                "control_type": "text",
                "label": "Status",
                "type": "string",
                "name": "status"
              }
            ],
            "type": "object"
          }
        ],
        "uuid": "6a7ac4c3-0186-41a8-8e64-37354d652b59"
      }
    ],
    "uuid": "4ec171d4-7224-450c-aa81-7fc578e975b2"
  },
  "config": [
    {
      "keyword": "application",
      "provider": "workato_api_platform",
      "skip_validation": false,
      "account_id": null
    },
    {
      "keyword": "application",
      "provider": "salesforce",
      "skip_validation": false,
      "account_id": {
        "zip_name": "Workspace Connections/sf_dev_account.connection.json",
        "name": "SF Dev Account",
        "folder": "Workspace Connections"
      }
    }
  ]
}